[{"stn_code": "AKA", "dest": "AKHAURA", "classes": [{"class": "SHOVAN"}]}, {"stn_code": "ALNR", "dest": "AOWLIA NAGAR", "classes": []}, {"stn_code": "BNNI", "dest": "BANANI", "classes": []}, {"stn_code": "BRAT", "dest": "BARHATTA", "classes": [{"class": "SHOVAN"}]}, {"stn_code": "BCI", "dest": "BHAIRAB_BAZAR", "classes": [{"class": "SHOVAN"}]}, {"stn_code": "BYI", "dest": "BHATIARY", "classes": []}, {"stn_code": "BYJ", "dest": "BIDDAGANJ", "classes": []}, {"stn_code": "DABB", "dest": "BIMAN_BANDAR", "classes": [{"class": "SHOVAN"}]}, {"stn_code": "CTG", "dest": "CHITTAGONG", "classes": [{"class": "F_BERTH"}, {"class": "F_CHAIR"}, {"class": "SHOVAN"}, {"class": "S_CHAIR"}]}, {"stn_code": "CML", "dest": "COMILLA", "classes": [{"class": "SHOVAN"}]}, {"stn_code": "DACT", "dest": "DA_CANTONMENT", "classes": []}, {"stn_code": "DWB", "dest": "DEWANGANJ_BAZAR", "classes": [{"class": "AC_S"}, {"class": "F_SEAT"}, {"class": "SNIGDHA"}, {"class": "S_CHAIR"}]}, {"stn_code": "DA", "dest": "DHAKA", "classes": [{"class": "AC_B"}, {"class": "AC_S"}, {"class": "F_BERTH"}, {"class": "F_CHAIR"}, {"class": "F_SEAT"}, {"class": "SHOVAN"}, {"class": "SNIGDHA"}, {"class": "S_CHAIR"}]}, {"stn_code": "DHV", "dest": "DHOALA", "classes": []}, {"stn_code": "DRT", "dest": "DURMUT", "classes": []}, {"stn_code": "FMN", "dest": "FATEMA NAGAR", "classes": []}, {"stn_code": "FNI", "dest": "FENI", "classes": [{"class": "SHOVAN"}]}, {"stn_code": "GFN", "dest": "GAFARGAON", "classes": [{"class": "F_SEAT"}, {"class": "SHOVAN"}, {"class": "SNIGDHA"}, {"class": "S_CHAIR"}]}, {"stn_code": "GRPM", "dest": "GOURIPUR_MYN", "classes": [{"class": "SHOVAN"}, {"class": "S_CHAIR"}]}, {"stn_code": "IPB", "dest": "ISLAMPUR_BAZAR", "classes": [{"class": "SNIGDHA"}, {"class": "S_CHAIR"}]}, {"stn_code": "JLX", "dest": "JAMALPUR_TOWN", "classes": [{"class": "F_CHAIR"}, {"class": "SHOVAN"}, {"class": "SNIGDHA"}, {"class": "S_CHAIR"}]}, {"stn_code": "JYR", "dest": "JAYDEBPUR", "classes": [{"class": "SHOVAN"}]}, {"stn_code": "KWY", "dest": "KAWRAIT", "classes": []}, {"stn_code": "KFJ", "dest": "KISHOREGANJ", "classes": [{"class": "SHOVAN"}, {"class": "S_CHAIR"}]}, {"stn_code": "KHIP", "dest": "KRISHI UNIVER.", "classes": []}, {"stn_code": "LKM", "dest": "LAKSAM", "classes": [{"class": "SHOVAN"}]}, {"stn_code": "MLDB", "dest": "MELANDAH_BAZAR", "classes": [{"class": "S_CHAIR"}]}, {"stn_code": "MGJN", "dest": "MOHONGANJ", "classes": [{"class": "SHOVAN"}, {"class": "SNIGDHA"}, {"class": "S_CHAIR"}]}, {"stn_code": "MHY", "dest": "MOSHAKHALI", "classes": []}, {"stn_code": "NND", "dest": "NANDINA", "classes": []}, {"stn_code": "NRQ", "dest": "NETROKONA", "classes": [{"class": "SHOVAN"}, {"class": "S_CHAIR"}]}, {"stn_code": "NNI", "dest": "NURUNDI", "classes": []}, {"stn_code": "PYP", "dest": "PYERPUR", "classes": []}, {"stn_code": "RAB", "dest": "RAJENDRAPUR", "classes": []}, {"stn_code": "SCD", "dest": "SARARCHAR", "classes": [{"class": "SHOVAN"}]}, {"stn_code": "SSI", "dest": "SARISHA_BARI", "classes": [{"class": "SHOVAN"}]}, {"stn_code": "SSK", "dest": "SATKHAMAER", "classes": []}, {"stn_code": "SZG", "dest": "SHEMGANJ", "classes": [{"class": "SHOVAN"}, {"class": "S_CHAIR"}]}, {"stn_code": "SPU", "dest": "SRIPUR", "classes": []}, {"stn_code": "TGI", "dest": "TANGI", "classes": []}, {"stn_code": "TKND", "dest": "TARAKANDI", "classes": [{"class": "F_SEAT"}, {"class": "SHOVAN"}]}, {"stn_code": "TGN", "dest": "TEJGON", "classes": []}, {"stn_code": "TKKN", "dest": "THAKURAKONA", "classes": []}]